cuckoofilter/__init__.py
cuckoofilter/bucket.py
cuckoofilter/cuckoofilter.py
cuckoofilter/utils.py
cuckoofilter-0.0.0.2.dist-info/LICENSE
cuckoofilter-0.0.0.2.dist-info/METADATA
cuckoofilter-0.0.0.2.dist-info/WHEEL
cuckoofilter-0.0.0.2.dist-info/top_level.txt
cuckoofilter-0.0.0.2.dist-info/RECORD
