Metadata-Version: 2.1
Name: cuckoofilter
Version: 0.0.0.2
Summary: Cuckoo Filter Implementation Using Python
Home-page: https://github.com/beaulian/cuckoofilter
Author: Jiawen Guan
Author-email: jesus.jiawen@gmail.com
License: GPL-3.0
Platform: UNKNOWN
Classifier: Development Status :: 5 - Production/Stable
Classifier: Intended Audience :: Developers
Classifier: Natural Language :: English
Classifier: License :: OSI Approved :: GNU General Public License (GPL)
Classifier: Programming Language :: Python
Classifier: Programming Language :: Python :: 2
Classifier: Programming Language :: Python :: 2.7
Classifier: Programming Language :: Python :: 3
Classifier: Programming Language :: Python :: 3.5
Classifier: Programming Language :: Python :: 3.6
Requires-Dist: mmh3
